{
  "Manchester City": "Manchester City",
  "Manchester United": "Manchester United",
  "Arsenal": "Arsenal",
  "Chelsea": "Chelsea",
  "Liverpool": "Liverpool",
  "Tottenham Hotspur": "Tottenham Hotspur",
  "Newcastle United": "Newcastle United",
  "West Ham United": "West Ham United",
  "Aston Villa": "Aston Villa",
  "Brighton and Hove Albion": "Brighton & Hove Albion",
  "Brentford": "Brentford",
  "Fulham": "Fulham",
  "Wolverhampton Wanderers": "Wolverhampton Wanderers",
  "Everton": "Everton",
  "Crystal Palace": "Crystal Palace",
  "Nottingham Forest": "Nottingham Forest",
  "Bournemouth": "Bournemouth",
  "Leicester City": "Leicester City",
  "Leeds United": "Leeds United",
  "Burnley": "Burnley",
  "Real Madrid": "Real Madrid CF",
  "Barcelona": "FC Barcelona",
  "Atletico Madrid": "Club Atl\u00e9tico de Madrid",
  "Sevilla": "Sevilla FC",
  "Real Sociedad": "Real Sociedad",
  "Athletic Club": "Athletic Club de Bilbao",
  "Valencia": "Valencia CF",
  "Villarreal": "Villarreal CF",
  "Betis": "Real Betis Balompi\u00e9",
  "Espanyol": "RCD Espanyol de Barcelona",
  "Osasuna": "CA Osasuna",
  "Getafe": "Getafe CF",
  "Celta Vigo": "Celta de Vigo",
  "Rayo Vallecano": "Rayo Vallecano de Madrid",
  "Mallorca": "RCD Mallorca",
  "Girona": "Girona FC",
  "Alaves": "Deportivo Alav\u00e9s",
  "Las Palmas": "UD Las Palmas",
  "Cadiz": "C\u00e1diz CF",
  "Granada": "Granada CF",
  "Inter Milan": "Inter",
  "AC Milan": "AC Milan",
  "Juventus": "Juventus",
  "AS Roma": "AS Roma",
  "Lazio": "SS Lazio",
  "Napoli": "SSC Napoli",
  "Atalanta": "Atalanta BC",
  "Fiorentina": "ACF Fiorentina",
  "Torino": "Torino FC",
  "Bologna": "Bologna FC 1909",
  "Udinese": "Udinese Calcio",
  "Sassuolo": "US Sassuolo Calcio",
  "Monza": "AC Monza",
  "Lecce": "US Lecce",
  "Cagliari": "Cagliari Calcio",
  "Frosinone": "Frosinone Calcio",
  "Hellas Verona": "Hellas Verona FC",
  "Genoa": "Genoa CFC",
  "Salernitana": "US Salernitana 1919",
  "Empoli": "Empoli FC",
  "Parma": "Parma Calcio 1913",
  "Como": "Como 1907",
  "Bayern Munich": "FC Bayern Munich",
  "Borussia Dortmund": "Borussia Dortmund",
  "RB Leipzig": "RasenBallsport Leipzig",
  "Bayer Leverkusen": "Bayer 04 Leverkusen",
  "Eintracht Frankfurt": "Eintracht Frankfurt",
  "Wolfsburg": "VfL Wolfsburg",
  "VfL Wolfsburg": "VfL Wolfsburg",
  "Borussia Monchengladbach": "Borussia M\u00f6nchengladbach",
  "Union Berlin": "1. FC Union Berlin",
  "SC Freiburg": "SC Freiburg",
  "Hoffenheim": "TSG 1899 Hoffenheim",
  "Mainz 05": "1. FSV Mainz 05",
  "Augsburg": "FC Augsburg",
  "Werder Bremen": "SV Werder Bremen",
  "Stuttgart": "VfB Stuttgart",
  "Bochum": "VfL Bochum 1848",
  "Koln": "1. FC K\u00f6ln",
  "1. FC Heidenheim 1846": "1. FC Heidenheim 1846",
  "Darmstadt 98": "SV Darmstadt 98"
}